sc3/__init__.py
sc3/__main__.py
sc3/_all.py
sc3/all.py
sc3/all_nrt.py
sc3/base/__init__.py
sc3/base/_hooks.py
sc3/base/_knownpaths.py
sc3/base/_midiinterface.py
sc3/base/_oscinterface.py
sc3/base/_osclib.py
sc3/base/_oscmatch.py
sc3/base/_taskq.py
sc3/base/absobject.py
sc3/base/all.py
sc3/base/builtins.py
sc3/base/classlibrary.py
sc3/base/clock.py
sc3/base/functions.py
sc3/base/main.py
sc3/base/midi.py
sc3/base/model.py
sc3/base/netaddr.py
sc3/base/operand.py
sc3/base/platform.py
sc3/base/play.py
sc3/base/responders.py
sc3/base/stream.py
sc3/base/systemactions.py
sc3/base/utils.py
sc3/seq/__init__.py
sc3/seq/all.py
sc3/seq/event.py
sc3/seq/eventstream.py
sc3/seq/patch.py
sc3/seq/pattern.py
sc3/seq/scale.py
sc3/seq/patterns/__init__.py
sc3/seq/patterns/eventpatterns.py
sc3/seq/patterns/filterpatterns.py
sc3/seq/patterns/funcpatterns.py
sc3/seq/patterns/listpatterns.py
sc3/seq/patterns/timepatterns.py
sc3/seq/patterns/valuepatterns.py
sc3/synth/__init__.py
sc3/synth/_engine.py
sc3/synth/_fmtrw.py
sc3/synth/_graphparam.py
sc3/synth/_nodewatcher.py
sc3/synth/_serverstatus.py
sc3/synth/_specialindex.py
sc3/synth/_volume.py
sc3/synth/all.py
sc3/synth/buffer.py
sc3/synth/bus.py
sc3/synth/envelope.py
sc3/synth/node.py
sc3/synth/recorder.py
sc3/synth/server.py
sc3/synth/spec.py
sc3/synth/synthdef.py
sc3/synth/synthdesc.py
sc3/synth/systemdefs.py
sc3/synth/ugen.py
sc3/synth/ugens/__init__.py
sc3/synth/ugens/beqsuite.py
sc3/synth/ugens/bufio.py
sc3/synth/ugens/chaos.py
sc3/synth/ugens/convolution.py
sc3/synth/ugens/delays.py
sc3/synth/ugens/demand.py
sc3/synth/ugens/diskio.py
sc3/synth/ugens/dynamics.py
sc3/synth/ugens/envgen.py
sc3/synth/ugens/fft.py
sc3/synth/ugens/filter.py
sc3/synth/ugens/foscillators.py
sc3/synth/ugens/gendyn.py
sc3/synth/ugens/grainugens.py
sc3/synth/ugens/hid.py
sc3/synth/ugens/hilbert.py
sc3/synth/ugens/infougens.py
sc3/synth/ugens/inout.py
sc3/synth/ugens/line.py
sc3/synth/ugens/machinelistening.py
sc3/synth/ugens/mix.py
sc3/synth/ugens/noise.py
sc3-1.1.3a0.dist-info/COPYING
sc3-1.1.3a0.dist-info/METADATA
sc3-1.1.3a0.dist-info/WHEEL
sc3-1.1.3a0.dist-info/top_level.txt
sc3-1.1.3a0.dist-info/RECORD
