Metadata-Version: 2.1
Name: sc3
Version: 1.1.3a0
Summary: SuperCollider library for Python
Home-page: https://github.com/smrg-lm/sc3
Author: Lucas Samaruga
Author-email: samarugalucas@gmail.com
License: GPLv3
Keywords: SuperCollider sound synthesis music-composition
Platform: Any
Classifier: Programming Language :: Python :: 3.6
Classifier: Programming Language :: Python :: 3.7
Classifier: Programming Language :: Python :: 3.8
Classifier: Programming Language :: Python :: 3.9
Classifier: Programming Language :: Python :: 3.10
Classifier: License :: OSI Approved :: GNU General Public License v3 (GPLv3)
Classifier: Operating System :: OS Independent
Classifier: Development Status :: 3 - Alpha
Requires-Python: >=3.6
License-File: COPYING
Provides-Extra: midi
Requires-Dist: mido ; extra == 'midi'
Requires-Dist: python-rtmidi ; extra == 'midi'
Provides-Extra: midi-nrt
Requires-Dist: mido ; extra == 'midi-nrt'
